altgraph/Dot.py
altgraph/Graph.py
altgraph/GraphAlgo.py
altgraph/GraphStat.py
altgraph/GraphUtil.py
altgraph/ObjectGraph.py
altgraph/__init__.py
altgraph-0.17.1.dist-info/LICENSE
altgraph-0.17.1.dist-info/METADATA
altgraph-0.17.1.dist-info/WHEEL
altgraph-0.17.1.dist-info/top_level.txt
altgraph-0.17.1.dist-info/zip-safe
altgraph-0.17.1.dist-info/RECORD
