Metadata-Version: 2.1
Name: altgraph
Version: 0.17.1
Summary: Python graph (network) package
Home-page: https://altgraph.readthedocs.io
Author: Ronald Oussoren
Author-email: ronaldoussoren@mac.com
Maintainer: Ronald Oussoren
Maintainer-email: ronaldoussoren@mac.com
License: MIT
Download-URL: http://pypi.python.org/pypi/altgraph
Keywords: graph
Platform: any
Classifier: Intended Audience :: Developers
Classifier: License :: OSI Approved :: MIT License
Classifier: Programming Language :: Python
Classifier: Programming Language :: Python :: 2
Classifier: Programming Language :: Python :: 2.7
Classifier: Programming Language :: Python :: 3
Classifier: Programming Language :: Python :: 3.4
Classifier: Programming Language :: Python :: 3.5
Classifier: Programming Language :: Python :: 3.6
Classifier: Programming Language :: Python :: 3.7
Classifier: Programming Language :: Python :: 3.8
Classifier: Programming Language :: Python :: 3.9
Classifier: Programming Language :: Python :: 3.10
Classifier: Topic :: Software Development :: Libraries :: Python Modules
Classifier: Topic :: Scientific/Engineering :: Mathematics
Classifier: Topic :: Scientific/Engineering :: Visualization
License-File: LICENSE
